<?xml version="1.0" encoding="UTF-8" standalone="no"?>
<source_library title="source library">
  <source name="Background" type="CTAIrfBackground" instrument="CTA">
    <spectrum type="PowerLaw">
      <parameter scale="1e+00" name="Prefactor" min="1e-7" max="1000" free="1" value="1.00000" />
      <parameter scale="-1.0" name="Index" min="0.0" max="+10.0" free="1" value="0.0" />
      <parameter scale="1.0" name="Scale" min="0.0" max="+10000000.0" free="0" value="300000.0" />
    </spectrum>
  </source>
  <source type="PointSource" name="Event616_0" tscalc="1">
    <spectrum type="FileFunction" file="/home/irene/cta/models/afterglow/Event616/spectra/spec_000_tin-1.100_tend-1.400.txt">
      <parameter scale="1e+00" name="Normalization" min="1e-7" max="1000" free="1" value="1.00000" />
    </spectrum>
    <spatialModel type="SkyDirFunction">
      <parameter scale="1.0" name="RA" min="-360" max="360" free="0" value="0" />
      <parameter scale="1.0" name="DEC" min="-90" max="90" free="0" value="0.75" />
    </spatialModel>
    <temporal type="LightCurve" file="/home/irene/cta/models/afterglow/Event616/lightcv/lc_000_tin-1.100_tend-1.400.fits">
      <parameter scale="1e+00" name="Normalization" min="0.0" max="1000.0" free="0" value="1.00000" />
    </temporal>
  </source>
  <source type="PointSource" name="Event616_1" tscalc="1">
    <spectrum type="FileFunction" file="/home/irene/cta/models/afterglow/Event616/spectra/spec_001_tin-1.400_tend-1.820.txt">
      <parameter scale="1e+00" name="Normalization" min="1e-7" max="1000" free="1" value="1.00000" />
    </spectrum>
    <spatialModel type="SkyDirFunction">
      <parameter scale="1.0" name="RA" min="-360" max="360" free="0" value="0" />
      <parameter scale="1.0" name="DEC" min="-90" max="90" free="0" value="0.75" />
    </spatialModel>
    <temporal type="LightCurve" file="/home/irene/cta/models/afterglow/Event616/lightcv/lc_001_tin-1.400_tend-1.820.fits">
      <parameter scale="1e+00" name="Normalization" min="0.0" max="1000.0" free="0" value="1.00000" />
    </temporal>
  </source>
  <source type="PointSource" name="Event616_2" tscalc="1">
    <spectrum type="FileFunction" file="/home/irene/cta/models/afterglow/Event616/spectra/spec_002_tin-1.820_tend-2.340.txt">
      <parameter scale="1e+00" name="Normalization" min="1e-7" max="1000" free="1" value="1.00000" />
    </spectrum>
    <spatialModel type="SkyDirFunction">
      <parameter scale="1.0" name="RA" min="-360" max="360" free="0" value="0" />
      <parameter scale="1.0" name="DEC" min="-90" max="90" free="0" value="0.75" />
    </spatialModel>
    <temporal type="LightCurve" file="/home/irene/cta/models/afterglow/Event616/lightcv/lc_002_tin-1.820_tend-2.340.fits">
      <parameter scale="1e+00" name="Normalization" min="0.0" max="1000.0" free="0" value="1.00000" />
    </temporal>
  </source>
  <source type="PointSource" name="Event616_3" tscalc="1">
    <spectrum type="FileFunction" file="/home/irene/cta/models/afterglow/Event616/spectra/spec_003_tin-2.340_tend-2.970.txt">
      <parameter scale="1e+00" name="Normalization" min="1e-7" max="1000" free="1" value="1.00000" />
    </spectrum>
    <spatialModel type="SkyDirFunction">
      <parameter scale="1.0" name="RA" min="-360" max="360" free="0" value="0" />
      <parameter scale="1.0" name="DEC" min="-90" max="90" free="0" value="0.75" />
    </spatialModel>
    <temporal type="LightCurve" file="/home/irene/cta/models/afterglow/Event616/lightcv/lc_003_tin-2.340_tend-2.970.fits">
      <parameter scale="1e+00" name="Normalization" min="0.0" max="1000.0" free="0" value="1.00000" />
    </temporal>
  </source>
  <source type="PointSource" name="Event616_4" tscalc="1">
    <spectrum type="FileFunction" file="/home/irene/cta/models/afterglow/Event616/spectra/spec_004_tin-2.970_tend-3.820.txt">
      <parameter scale="1e+00" name="Normalization" min="1e-7" max="1000" free="1" value="1.00000" />
    </spectrum>
    <spatialModel type="SkyDirFunction">
      <parameter scale="1.0" name="RA" min="-360" max="360" free="0" value="0" />
      <parameter scale="1.0" name="DEC" min="-90" max="90" free="0" value="0.75" />
    </spatialModel>
    <temporal type="LightCurve" file="/home/irene/cta/models/afterglow/Event616/lightcv/lc_004_tin-2.970_tend-3.820.fits">
      <parameter scale="1e+00" name="Normalization" min="0.0" max="1000.0" free="0" value="1.00000" />
    </temporal>
  </source>
  <source type="PointSource" name="Event616_5" tscalc="1">
    <spectrum type="FileFunction" file="/home/irene/cta/models/afterglow/Event616/spectra/spec_005_tin-3.820_tend-4.880.txt">
      <parameter scale="1e+00" name="Normalization" min="1e-7" max="1000" free="1" value="1.00000" />
    </spectrum>
    <spatialModel type="SkyDirFunction">
      <parameter scale="1.0" name="RA" min="-360" max="360" free="0" value="0" />
      <parameter scale="1.0" name="DEC" min="-90" max="90" free="0" value="0.75" />
    </spatialModel>
    <temporal type="LightCurve" file="/home/irene/cta/models/afterglow/Event616/lightcv/lc_005_tin-3.820_tend-4.880.fits">
      <parameter scale="1e+00" name="Normalization" min="0.0" max="1000.0" free="0" value="1.00000" />
    </temporal>
  </source>
  <source type="PointSource" name="Event616_6" tscalc="1">
    <spectrum type="FileFunction" file="/home/irene/cta/models/afterglow/Event616/spectra/spec_006_tin-4.880_tend-6.160.txt">
      <parameter scale="1e+00" name="Normalization" min="1e-7" max="1000" free="1" value="1.00000" />
    </spectrum>
    <spatialModel type="SkyDirFunction">
      <parameter scale="1.0" name="RA" min="-360" max="360" free="0" value="0" />
      <parameter scale="1.0" name="DEC" min="-90" max="90" free="0" value="0.75" />
    </spatialModel>
    <temporal type="LightCurve" file="/home/irene/cta/models/afterglow/Event616/lightcv/lc_006_tin-4.880_tend-6.160.fits">
      <parameter scale="1e+00" name="Normalization" min="0.0" max="1000.0" free="0" value="1.00000" />
    </temporal>
  </source>
  <source type="PointSource" name="Event616_7" tscalc="1">
    <spectrum type="FileFunction" file="/home/irene/cta/models/afterglow/Event616/spectra/spec_007_tin-6.160_tend-7.750.txt">
      <parameter scale="1e+00" name="Normalization" min="1e-7" max="1000" free="1" value="1.00000" />
    </spectrum>
    <spatialModel type="SkyDirFunction">
      <parameter scale="1.0" name="RA" min="-360" max="360" free="0" value="0" />
      <parameter scale="1.0" name="DEC" min="-90" max="90" free="0" value="0.75" />
    </spatialModel>
    <temporal type="LightCurve" file="/home/irene/cta/models/afterglow/Event616/lightcv/lc_007_tin-6.160_tend-7.750.fits">
      <parameter scale="1e+00" name="Normalization" min="0.0" max="1000.0" free="0" value="1.00000" />
    </temporal>
  </source>
  <source type="PointSource" name="Event616_8" tscalc="1">
    <spectrum type="FileFunction" file="/home/irene/cta/models/afterglow/Event616/spectra/spec_008_tin-7.750_tend-9.780.txt">
      <parameter scale="1e+00" name="Normalization" min="1e-7" max="1000" free="1" value="1.00000" />
    </spectrum>
    <spatialModel type="SkyDirFunction">
      <parameter scale="1.0" name="RA" min="-360" max="360" free="0" value="0" />
      <parameter scale="1.0" name="DEC" min="-90" max="90" free="0" value="0.75" />
    </spatialModel>
    <temporal type="LightCurve" file="/home/irene/cta/models/afterglow/Event616/lightcv/lc_008_tin-7.750_tend-9.780.fits">
      <parameter scale="1e+00" name="Normalization" min="0.0" max="1000.0" free="0" value="1.00000" />
    </temporal>
  </source>
  <source type="PointSource" name="Event616_9" tscalc="1">
    <spectrum type="FileFunction" file="/home/irene/cta/models/afterglow/Event616/spectra/spec_009_tin-9.780_tend-12.200.txt">
      <parameter scale="1e+00" name="Normalization" min="1e-7" max="1000" free="1" value="1.00000" />
    </spectrum>
    <spatialModel type="SkyDirFunction">
      <parameter scale="1.0" name="RA" min="-360" max="360" free="0" value="0" />
      <parameter scale="1.0" name="DEC" min="-90" max="90" free="0" value="0.75" />
    </spatialModel>
    <temporal type="LightCurve" file="/home/irene/cta/models/afterglow/Event616/lightcv/lc_009_tin-9.780_tend-12.200.fits">
      <parameter scale="1e+00" name="Normalization" min="0.0" max="1000.0" free="0" value="1.00000" />
    </temporal>
  </source>
  <source type="PointSource" name="Event616_10" tscalc="1">
    <spectrum type="FileFunction" file="/home/irene/cta/models/afterglow/Event616/spectra/spec_010_tin-12.200_tend-15.300.txt">
      <parameter scale="1e+00" name="Normalization" min="1e-7" max="1000" free="1" value="1.00000" />
    </spectrum>
    <spatialModel type="SkyDirFunction">
      <parameter scale="1.0" name="RA" min="-360" max="360" free="0" value="0" />
      <parameter scale="1.0" name="DEC" min="-90" max="90" free="0" value="0.75" />
    </spatialModel>
    <temporal type="LightCurve" file="/home/irene/cta/models/afterglow/Event616/lightcv/lc_010_tin-12.200_tend-15.300.fits">
      <parameter scale="1e+00" name="Normalization" min="0.0" max="1000.0" free="0" value="1.00000" />
    </temporal>
  </source>
  <source type="PointSource" name="Event616_11" tscalc="1">
    <spectrum type="FileFunction" file="/home/irene/cta/models/afterglow/Event616/spectra/spec_011_tin-15.300_tend-19.200.txt">
      <parameter scale="1e+00" name="Normalization" min="1e-7" max="1000" free="1" value="1.00000" />
    </spectrum>
    <spatialModel type="SkyDirFunction">
      <parameter scale="1.0" name="RA" min="-360" max="360" free="0" value="0" />
      <parameter scale="1.0" name="DEC" min="-90" max="90" free="0" value="0.75" />
    </spatialModel>
    <temporal type="LightCurve" file="/home/irene/cta/models/afterglow/Event616/lightcv/lc_011_tin-15.300_tend-19.200.fits">
      <parameter scale="1e+00" name="Normalization" min="0.0" max="1000.0" free="0" value="1.00000" />
    </temporal>
  </source>
  <source type="PointSource" name="Event616_12" tscalc="1">
    <spectrum type="FileFunction" file="/home/irene/cta/models/afterglow/Event616/spectra/spec_012_tin-19.200_tend-24.100.txt">
      <parameter scale="1e+00" name="Normalization" min="1e-7" max="1000" free="1" value="1.00000" />
    </spectrum>
    <spatialModel type="SkyDirFunction">
      <parameter scale="1.0" name="RA" min="-360" max="360" free="0" value="0" />
      <parameter scale="1.0" name="DEC" min="-90" max="90" free="0" value="0.75" />
    </spatialModel>
    <temporal type="LightCurve" file="/home/irene/cta/models/afterglow/Event616/lightcv/lc_012_tin-19.200_tend-24.100.fits">
      <parameter scale="1e+00" name="Normalization" min="0.0" max="1000.0" free="0" value="1.00000" />
    </temporal>
  </source>
  <source type="PointSource" name="Event616_13" tscalc="1">
    <spectrum type="FileFunction" file="/home/irene/cta/models/afterglow/Event616/spectra/spec_013_tin-24.100_tend-30.200.txt">
      <parameter scale="1e+00" name="Normalization" min="1e-7" max="1000" free="1" value="1.00000" />
    </spectrum>
    <spatialModel type="SkyDirFunction">
      <parameter scale="1.0" name="RA" min="-360" max="360" free="0" value="0" />
      <parameter scale="1.0" name="DEC" min="-90" max="90" free="0" value="0.75" />
    </spatialModel>
    <temporal type="LightCurve" file="/home/irene/cta/models/afterglow/Event616/lightcv/lc_013_tin-24.100_tend-30.200.fits">
      <parameter scale="1e+00" name="Normalization" min="0.0" max="1000.0" free="0" value="1.00000" />
    </temporal>
  </source>
  <source type="PointSource" name="Event616_14" tscalc="1">
    <spectrum type="FileFunction" file="/home/irene/cta/models/afterglow/Event616/spectra/spec_014_tin-30.200_tend-37.800.txt">
      <parameter scale="1e+00" name="Normalization" min="1e-7" max="1000" free="1" value="1.00000" />
    </spectrum>
    <spatialModel type="SkyDirFunction">
      <parameter scale="1.0" name="RA" min="-360" max="360" free="0" value="0" />
      <parameter scale="1.0" name="DEC" min="-90" max="90" free="0" value="0.75" />
    </spatialModel>
    <temporal type="LightCurve" file="/home/irene/cta/models/afterglow/Event616/lightcv/lc_014_tin-30.200_tend-37.800.fits">
      <parameter scale="1e+00" name="Normalization" min="0.0" max="1000.0" free="0" value="1.00000" />
    </temporal>
  </source>
  <source type="PointSource" name="Event616_15" tscalc="1">
    <spectrum type="FileFunction" file="/home/irene/cta/models/afterglow/Event616/spectra/spec_015_tin-37.800_tend-47.300.txt">
      <parameter scale="1e+00" name="Normalization" min="1e-7" max="1000" free="1" value="1.00000" />
    </spectrum>
    <spatialModel type="SkyDirFunction">
      <parameter scale="1.0" name="RA" min="-360" max="360" free="0" value="0" />
      <parameter scale="1.0" name="DEC" min="-90" max="90" free="0" value="0.75" />
    </spatialModel>
    <temporal type="LightCurve" file="/home/irene/cta/models/afterglow/Event616/lightcv/lc_015_tin-37.800_tend-47.300.fits">
      <parameter scale="1e+00" name="Normalization" min="0.0" max="1000.0" free="0" value="1.00000" />
    </temporal>
  </source>
  <source type="PointSource" name="Event616_16" tscalc="1">
    <spectrum type="FileFunction" file="/home/irene/cta/models/afterglow/Event616/spectra/spec_016_tin-47.300_tend-59.200.txt">
      <parameter scale="1e+00" name="Normalization" min="1e-7" max="1000" free="1" value="1.00000" />
    </spectrum>
    <spatialModel type="SkyDirFunction">
      <parameter scale="1.0" name="RA" min="-360" max="360" free="0" value="0" />
      <parameter scale="1.0" name="DEC" min="-90" max="90" free="0" value="0.75" />
    </spatialModel>
    <temporal type="LightCurve" file="/home/irene/cta/models/afterglow/Event616/lightcv/lc_016_tin-47.300_tend-59.200.fits">
      <parameter scale="1e+00" name="Normalization" min="0.0" max="1000.0" free="0" value="1.00000" />
    </temporal>
  </source>
  <source type="PointSource" name="Event616_17" tscalc="1">
    <spectrum type="FileFunction" file="/home/irene/cta/models/afterglow/Event616/spectra/spec_017_tin-59.200_tend-74.400.txt">
      <parameter scale="1e+00" name="Normalization" min="1e-7" max="1000" free="1" value="1.00000" />
    </spectrum>
    <spatialModel type="SkyDirFunction">
      <parameter scale="1.0" name="RA" min="-360" max="360" free="0" value="0" />
      <parameter scale="1.0" name="DEC" min="-90" max="90" free="0" value="0.75" />
    </spatialModel>
    <temporal type="LightCurve" file="/home/irene/cta/models/afterglow/Event616/lightcv/lc_017_tin-59.200_tend-74.400.fits">
      <parameter scale="1e+00" name="Normalization" min="0.0" max="1000.0" free="0" value="1.00000" />
    </temporal>
  </source>
  <source type="PointSource" name="Event616_18" tscalc="1">
    <spectrum type="FileFunction" file="/home/irene/cta/models/afterglow/Event616/spectra/spec_018_tin-74.400_tend-93.200.txt">
      <parameter scale="1e+00" name="Normalization" min="1e-7" max="1000" free="1" value="1.00000" />
    </spectrum>
    <spatialModel type="SkyDirFunction">
      <parameter scale="1.0" name="RA" min="-360" max="360" free="0" value="0" />
      <parameter scale="1.0" name="DEC" min="-90" max="90" free="0" value="0.75" />
    </spatialModel>
    <temporal type="LightCurve" file="/home/irene/cta/models/afterglow/Event616/lightcv/lc_018_tin-74.400_tend-93.200.fits">
      <parameter scale="1e+00" name="Normalization" min="0.0" max="1000.0" free="0" value="1.00000" />
    </temporal>
  </source>
  <source type="PointSource" name="Event616_19" tscalc="1">
    <spectrum type="FileFunction" file="/home/irene/cta/models/afterglow/Event616/spectra/spec_019_tin-93.200_tend-118.000.txt">
      <parameter scale="1e+00" name="Normalization" min="1e-7" max="1000" free="1" value="1.00000" />
    </spectrum>
    <spatialModel type="SkyDirFunction">
      <parameter scale="1.0" name="RA" min="-360" max="360" free="0" value="0" />
      <parameter scale="1.0" name="DEC" min="-90" max="90" free="0" value="0.75" />
    </spatialModel>
    <temporal type="LightCurve" file="/home/irene/cta/models/afterglow/Event616/lightcv/lc_019_tin-93.200_tend-118.000.fits">
      <parameter scale="1e+00" name="Normalization" min="0.0" max="1000.0" free="0" value="1.00000" />
    </temporal>
  </source>
  <source type="PointSource" name="Event616_20" tscalc="1">
    <spectrum type="FileFunction" file="/home/irene/cta/models/afterglow/Event616/spectra/spec_020_tin-118.000_tend-148.000.txt">
      <parameter scale="1e+00" name="Normalization" min="1e-7" max="1000" free="1" value="1.00000" />
    </spectrum>
    <spatialModel type="SkyDirFunction">
      <parameter scale="1.0" name="RA" min="-360" max="360" free="0" value="0" />
      <parameter scale="1.0" name="DEC" min="-90" max="90" free="0" value="0.75" />
    </spatialModel>
    <temporal type="LightCurve" file="/home/irene/cta/models/afterglow/Event616/lightcv/lc_020_tin-118.000_tend-148.000.fits">
      <parameter scale="1e+00" name="Normalization" min="0.0" max="1000.0" free="0" value="1.00000" />
    </temporal>
  </source>
  <source type="PointSource" name="Event616_21" tscalc="1">
    <spectrum type="FileFunction" file="/home/irene/cta/models/afterglow/Event616/spectra/spec_021_tin-148.000_tend-187.000.txt">
      <parameter scale="1e+00" name="Normalization" min="1e-7" max="1000" free="1" value="1.00000" />
    </spectrum>
    <spatialModel type="SkyDirFunction">
      <parameter scale="1.0" name="RA" min="-360" max="360" free="0" value="0" />
      <parameter scale="1.0" name="DEC" min="-90" max="90" free="0" value="0.75" />
    </spatialModel>
    <temporal type="LightCurve" file="/home/irene/cta/models/afterglow/Event616/lightcv/lc_021_tin-148.000_tend-187.000.fits">
      <parameter scale="1e+00" name="Normalization" min="0.0" max="1000.0" free="0" value="1.00000" />
    </temporal>
  </source>
  <source type="PointSource" name="Event616_22" tscalc="1">
    <spectrum type="FileFunction" file="/home/irene/cta/models/afterglow/Event616/spectra/spec_022_tin-187.000_tend-234.000.txt">
      <parameter scale="1e+00" name="Normalization" min="1e-7" max="1000" free="1" value="1.00000" />
    </spectrum>
    <spatialModel type="SkyDirFunction">
      <parameter scale="1.0" name="RA" min="-360" max="360" free="0" value="0" />
      <parameter scale="1.0" name="DEC" min="-90" max="90" free="0" value="0.75" />
    </spatialModel>
    <temporal type="LightCurve" file="/home/irene/cta/models/afterglow/Event616/lightcv/lc_022_tin-187.000_tend-234.000.fits">
      <parameter scale="1e+00" name="Normalization" min="0.0" max="1000.0" free="0" value="1.00000" />
    </temporal>
  </source>
  <source type="PointSource" name="Event616_23" tscalc="1">
    <spectrum type="FileFunction" file="/home/irene/cta/models/afterglow/Event616/spectra/spec_023_tin-234.000_tend-294.000.txt">
      <parameter scale="1e+00" name="Normalization" min="1e-7" max="1000" free="1" value="1.00000" />
    </spectrum>
    <spatialModel type="SkyDirFunction">
      <parameter scale="1.0" name="RA" min="-360" max="360" free="0" value="0" />
      <parameter scale="1.0" name="DEC" min="-90" max="90" free="0" value="0.75" />
    </spatialModel>
    <temporal type="LightCurve" file="/home/irene/cta/models/afterglow/Event616/lightcv/lc_023_tin-234.000_tend-294.000.fits">
      <parameter scale="1e+00" name="Normalization" min="0.0" max="1000.0" free="0" value="1.00000" />
    </temporal>
  </source>
  <source type="PointSource" name="Event616_24" tscalc="1">
    <spectrum type="FileFunction" file="/home/irene/cta/models/afterglow/Event616/spectra/spec_024_tin-294.000_tend-369.000.txt">
      <parameter scale="1e+00" name="Normalization" min="1e-7" max="1000" free="1" value="1.00000" />
    </spectrum>
    <spatialModel type="SkyDirFunction">
      <parameter scale="1.0" name="RA" min="-360" max="360" free="0" value="0" />
      <parameter scale="1.0" name="DEC" min="-90" max="90" free="0" value="0.75" />
    </spatialModel>
    <temporal type="LightCurve" file="/home/irene/cta/models/afterglow/Event616/lightcv/lc_024_tin-294.000_tend-369.000.fits">
      <parameter scale="1e+00" name="Normalization" min="0.0" max="1000.0" free="0" value="1.00000" />
    </temporal>
  </source>
  <source type="PointSource" name="Event616_25" tscalc="1">
    <spectrum type="FileFunction" file="/home/irene/cta/models/afterglow/Event616/spectra/spec_025_tin-369.000_tend-462.000.txt">
      <parameter scale="1e+00" name="Normalization" min="1e-7" max="1000" free="1" value="1.00000" />
    </spectrum>
    <spatialModel type="SkyDirFunction">
      <parameter scale="1.0" name="RA" min="-360" max="360" free="0" value="0" />
      <parameter scale="1.0" name="DEC" min="-90" max="90" free="0" value="0.75" />
    </spatialModel>
    <temporal type="LightCurve" file="/home/irene/cta/models/afterglow/Event616/lightcv/lc_025_tin-369.000_tend-462.000.fits">
      <parameter scale="1e+00" name="Normalization" min="0.0" max="1000.0" free="0" value="1.00000" />
    </temporal>
  </source>
  <source type="PointSource" name="Event616_26" tscalc="1">
    <spectrum type="FileFunction" file="/home/irene/cta/models/afterglow/Event616/spectra/spec_026_tin-462.000_tend-584.000.txt">
      <parameter scale="1e+00" name="Normalization" min="1e-7" max="1000" free="1" value="1.00000" />
    </spectrum>
    <spatialModel type="SkyDirFunction">
      <parameter scale="1.0" name="RA" min="-360" max="360" free="0" value="0" />
      <parameter scale="1.0" name="DEC" min="-90" max="90" free="0" value="0.75" />
    </spatialModel>
    <temporal type="LightCurve" file="/home/irene/cta/models/afterglow/Event616/lightcv/lc_026_tin-462.000_tend-584.000.fits">
      <parameter scale="1e+00" name="Normalization" min="0.0" max="1000.0" free="0" value="1.00000" />
    </temporal>
  </source>
  <source type="PointSource" name="Event616_27" tscalc="1">
    <spectrum type="FileFunction" file="/home/irene/cta/models/afterglow/Event616/spectra/spec_027_tin-584.000_tend-733.000.txt">
      <parameter scale="1e+00" name="Normalization" min="1e-7" max="1000" free="1" value="1.00000" />
    </spectrum>
    <spatialModel type="SkyDirFunction">
      <parameter scale="1.0" name="RA" min="-360" max="360" free="0" value="0" />
      <parameter scale="1.0" name="DEC" min="-90" max="90" free="0" value="0.75" />
    </spatialModel>
    <temporal type="LightCurve" file="/home/irene/cta/models/afterglow/Event616/lightcv/lc_027_tin-584.000_tend-733.000.fits">
      <parameter scale="1e+00" name="Normalization" min="0.0" max="1000.0" free="0" value="1.00000" />
    </temporal>
  </source>
  <source type="PointSource" name="Event616_28" tscalc="1">
    <spectrum type="FileFunction" file="/home/irene/cta/models/afterglow/Event616/spectra/spec_028_tin-733.000_tend-930.000.txt">
      <parameter scale="1e+00" name="Normalization" min="1e-7" max="1000" free="1" value="1.00000" />
    </spectrum>
    <spatialModel type="SkyDirFunction">
      <parameter scale="1.0" name="RA" min="-360" max="360" free="0" value="0" />
      <parameter scale="1.0" name="DEC" min="-90" max="90" free="0" value="0.75" />
    </spatialModel>
    <temporal type="LightCurve" file="/home/irene/cta/models/afterglow/Event616/lightcv/lc_028_tin-733.000_tend-930.000.fits">
      <parameter scale="1e+00" name="Normalization" min="0.0" max="1000.0" free="0" value="1.00000" />
    </temporal>
  </source>
  <source type="PointSource" name="Event616_29" tscalc="1">
    <spectrum type="FileFunction" file="/home/irene/cta/models/afterglow/Event616/spectra/spec_029_tin-930.000_tend-1170.000.txt">
      <parameter scale="1e+00" name="Normalization" min="1e-7" max="1000" free="1" value="1.00000" />
    </spectrum>
    <spatialModel type="SkyDirFunction">
      <parameter scale="1.0" name="RA" min="-360" max="360" free="0" value="0" />
      <parameter scale="1.0" name="DEC" min="-90" max="90" free="0" value="0.75" />
    </spatialModel>
    <temporal type="LightCurve" file="/home/irene/cta/models/afterglow/Event616/lightcv/lc_029_tin-930.000_tend-1170.000.fits">
      <parameter scale="1e+00" name="Normalization" min="0.0" max="1000.0" free="0" value="1.00000" />
    </temporal>
  </source>
  <source type="PointSource" name="Event616_30" tscalc="1">
    <spectrum type="FileFunction" file="/home/irene/cta/models/afterglow/Event616/spectra/spec_030_tin-1170.000_tend-1480.000.txt">
      <parameter scale="1e+00" name="Normalization" min="1e-7" max="1000" free="1" value="1.00000" />
    </spectrum>
    <spatialModel type="SkyDirFunction">
      <parameter scale="1.0" name="RA" min="-360" max="360" free="0" value="0" />
      <parameter scale="1.0" name="DEC" min="-90" max="90" free="0" value="0.75" />
    </spatialModel>
    <temporal type="LightCurve" file="/home/irene/cta/models/afterglow/Event616/lightcv/lc_030_tin-1170.000_tend-1480.000.fits">
      <parameter scale="1e+00" name="Normalization" min="0.0" max="1000.0" free="0" value="1.00000" />
    </temporal>
  </source>
  <source type="PointSource" name="Event616_31" tscalc="1">
    <spectrum type="FileFunction" file="/home/irene/cta/models/afterglow/Event616/spectra/spec_031_tin-1480.000_tend-1850.000.txt">
      <parameter scale="1e+00" name="Normalization" min="1e-7" max="1000" free="1" value="1.00000" />
    </spectrum>
    <spatialModel type="SkyDirFunction">
      <parameter scale="1.0" name="RA" min="-360" max="360" free="0" value="0" />
      <parameter scale="1.0" name="DEC" min="-90" max="90" free="0" value="0.75" />
    </spatialModel>
    <temporal type="LightCurve" file="/home/irene/cta/models/afterglow/Event616/lightcv/lc_031_tin-1480.000_tend-1850.000.fits">
      <parameter scale="1e+00" name="Normalization" min="0.0" max="1000.0" free="0" value="1.00000" />
    </temporal>
  </source>
  <source type="PointSource" name="Event616_32" tscalc="1">
    <spectrum type="FileFunction" file="/home/irene/cta/models/afterglow/Event616/spectra/spec_032_tin-1850.000_tend-2340.000.txt">
      <parameter scale="1e+00" name="Normalization" min="1e-7" max="1000" free="1" value="1.00000" />
    </spectrum>
    <spatialModel type="SkyDirFunction">
      <parameter scale="1.0" name="RA" min="-360" max="360" free="0" value="0" />
      <parameter scale="1.0" name="DEC" min="-90" max="90" free="0" value="0.75" />
    </spatialModel>
    <temporal type="LightCurve" file="/home/irene/cta/models/afterglow/Event616/lightcv/lc_032_tin-1850.000_tend-2340.000.fits">
      <parameter scale="1e+00" name="Normalization" min="0.0" max="1000.0" free="0" value="1.00000" />
    </temporal>
  </source>
  <source type="PointSource" name="Event616_33" tscalc="1">
    <spectrum type="FileFunction" file="/home/irene/cta/models/afterglow/Event616/spectra/spec_033_tin-2340.000_tend-2970.000.txt">
      <parameter scale="1e+00" name="Normalization" min="1e-7" max="1000" free="1" value="1.00000" />
    </spectrum>
    <spatialModel type="SkyDirFunction">
      <parameter scale="1.0" name="RA" min="-360" max="360" free="0" value="0" />
      <parameter scale="1.0" name="DEC" min="-90" max="90" free="0" value="0.75" />
    </spatialModel>
    <temporal type="LightCurve" file="/home/irene/cta/models/afterglow/Event616/lightcv/lc_033_tin-2340.000_tend-2970.000.fits">
      <parameter scale="1e+00" name="Normalization" min="0.0" max="1000.0" free="0" value="1.00000" />
    </temporal>
  </source>
  <source type="PointSource" name="Event616_34" tscalc="1">
    <spectrum type="FileFunction" file="/home/irene/cta/models/afterglow/Event616/spectra/spec_034_tin-2970.000_tend-3730.000.txt">
      <parameter scale="1e+00" name="Normalization" min="1e-7" max="1000" free="1" value="1.00000" />
    </spectrum>
    <spatialModel type="SkyDirFunction">
      <parameter scale="1.0" name="RA" min="-360" max="360" free="0" value="0" />
      <parameter scale="1.0" name="DEC" min="-90" max="90" free="0" value="0.75" />
    </spatialModel>
    <temporal type="LightCurve" file="/home/irene/cta/models/afterglow/Event616/lightcv/lc_034_tin-2970.000_tend-3730.000.fits">
      <parameter scale="1e+00" name="Normalization" min="0.0" max="1000.0" free="0" value="1.00000" />
    </temporal>
  </source>
  <source type="PointSource" name="Event616_35" tscalc="1">
    <spectrum type="FileFunction" file="/home/irene/cta/models/afterglow/Event616/spectra/spec_035_tin-3730.000_tend-4710.000.txt">
      <parameter scale="1e+00" name="Normalization" min="1e-7" max="1000" free="1" value="1.00000" />
    </spectrum>
    <spatialModel type="SkyDirFunction">
      <parameter scale="1.0" name="RA" min="-360" max="360" free="0" value="0" />
      <parameter scale="1.0" name="DEC" min="-90" max="90" free="0" value="0.75" />
    </spatialModel>
    <temporal type="LightCurve" file="/home/irene/cta/models/afterglow/Event616/lightcv/lc_035_tin-3730.000_tend-4710.000.fits">
      <parameter scale="1e+00" name="Normalization" min="0.0" max="1000.0" free="0" value="1.00000" />
    </temporal>
  </source>
  <source type="PointSource" name="Event616_36" tscalc="1">
    <spectrum type="FileFunction" file="/home/irene/cta/models/afterglow/Event616/spectra/spec_036_tin-4710.000_tend-5980.000.txt">
      <parameter scale="1e+00" name="Normalization" min="1e-7" max="1000" free="1" value="1.00000" />
    </spectrum>
    <spatialModel type="SkyDirFunction">
      <parameter scale="1.0" name="RA" min="-360" max="360" free="0" value="0" />
      <parameter scale="1.0" name="DEC" min="-90" max="90" free="0" value="0.75" />
    </spatialModel>
    <temporal type="LightCurve" file="/home/irene/cta/models/afterglow/Event616/lightcv/lc_036_tin-4710.000_tend-5980.000.fits">
      <parameter scale="1e+00" name="Normalization" min="0.0" max="1000.0" free="0" value="1.00000" />
    </temporal>
  </source>
  <source type="PointSource" name="Event616_37" tscalc="1">
    <spectrum type="FileFunction" file="/home/irene/cta/models/afterglow/Event616/spectra/spec_037_tin-5980.000_tend-7670.000.txt">
      <parameter scale="1e+00" name="Normalization" min="1e-7" max="1000" free="1" value="1.00000" />
    </spectrum>
    <spatialModel type="SkyDirFunction">
      <parameter scale="1.0" name="RA" min="-360" max="360" free="0" value="0" />
      <parameter scale="1.0" name="DEC" min="-90" max="90" free="0" value="0.75" />
    </spatialModel>
    <temporal type="LightCurve" file="/home/irene/cta/models/afterglow/Event616/lightcv/lc_037_tin-5980.000_tend-7670.000.fits">
      <parameter scale="1e+00" name="Normalization" min="0.0" max="1000.0" free="0" value="1.00000" />
    </temporal>
  </source>
  <source type="PointSource" name="Event616_38" tscalc="1">
    <spectrum type="FileFunction" file="/home/irene/cta/models/afterglow/Event616/spectra/spec_038_tin-7670.000_tend-9660.000.txt">
      <parameter scale="1e+00" name="Normalization" min="1e-7" max="1000" free="1" value="1.00000" />
    </spectrum>
    <spatialModel type="SkyDirFunction">
      <parameter scale="1.0" name="RA" min="-360" max="360" free="0" value="0" />
      <parameter scale="1.0" name="DEC" min="-90" max="90" free="0" value="0.75" />
    </spatialModel>
    <temporal type="LightCurve" file="/home/irene/cta/models/afterglow/Event616/lightcv/lc_038_tin-7670.000_tend-9660.000.fits">
      <parameter scale="1e+00" name="Normalization" min="0.0" max="1000.0" free="0" value="1.00000" />
    </temporal>
  </source>
  <source type="PointSource" name="Event616_39" tscalc="1">
    <spectrum type="FileFunction" file="/home/irene/cta/models/afterglow/Event616/spectra/spec_039_tin-9660.000_tend-12300.000.txt">
      <parameter scale="1e+00" name="Normalization" min="1e-7" max="1000" free="1" value="1.00000" />
    </spectrum>
    <spatialModel type="SkyDirFunction">
      <parameter scale="1.0" name="RA" min="-360" max="360" free="0" value="0" />
      <parameter scale="1.0" name="DEC" min="-90" max="90" free="0" value="0.75" />
    </spatialModel>
    <temporal type="LightCurve" file="/home/irene/cta/models/afterglow/Event616/lightcv/lc_039_tin-9660.000_tend-12300.000.fits">
      <parameter scale="1e+00" name="Normalization" min="0.0" max="1000.0" free="0" value="1.00000" />
    </temporal>
  </source>
  <source type="PointSource" name="Event616_40" tscalc="1">
    <spectrum type="FileFunction" file="/home/irene/cta/models/afterglow/Event616/spectra/spec_040_tin-12300.000_tend-15700.000.txt">
      <parameter scale="1e+00" name="Normalization" min="1e-7" max="1000" free="1" value="1.00000" />
    </spectrum>
    <spatialModel type="SkyDirFunction">
      <parameter scale="1.0" name="RA" min="-360" max="360" free="0" value="0" />
      <parameter scale="1.0" name="DEC" min="-90" max="90" free="0" value="0.75" />
    </spatialModel>
    <temporal type="LightCurve" file="/home/irene/cta/models/afterglow/Event616/lightcv/lc_040_tin-12300.000_tend-15700.000.fits">
      <parameter scale="1e+00" name="Normalization" min="0.0" max="1000.0" free="0" value="1.00000" />
    </temporal>
  </source>
  <source type="PointSource" name="Event616_41" tscalc="1">
    <spectrum type="FileFunction" file="/home/irene/cta/models/afterglow/Event616/spectra/spec_041_tin-15700.000_tend-19600.000.txt">
      <parameter scale="1e+00" name="Normalization" min="1e-7" max="1000" free="1" value="1.00000" />
    </spectrum>
    <spatialModel type="SkyDirFunction">
      <parameter scale="1.0" name="RA" min="-360" max="360" free="0" value="0" />
      <parameter scale="1.0" name="DEC" min="-90" max="90" free="0" value="0.75" />
    </spatialModel>
    <temporal type="LightCurve" file="/home/irene/cta/models/afterglow/Event616/lightcv/lc_041_tin-15700.000_tend-19600.000.fits">
      <parameter scale="1e+00" name="Normalization" min="0.0" max="1000.0" free="0" value="1.00000" />
    </temporal>
  </source>
  <source type="PointSource" name="Event616_42" tscalc="1">
    <spectrum type="FileFunction" file="/home/irene/cta/models/afterglow/Event616/spectra/spec_042_tin-19600.000_tend-24700.000.txt">
      <parameter scale="1e+00" name="Normalization" min="1e-7" max="1000" free="1" value="1.00000" />
    </spectrum>
    <spatialModel type="SkyDirFunction">
      <parameter scale="1.0" name="RA" min="-360" max="360" free="0" value="0" />
      <parameter scale="1.0" name="DEC" min="-90" max="90" free="0" value="0.75" />
    </spatialModel>
    <temporal type="LightCurve" file="/home/irene/cta/models/afterglow/Event616/lightcv/lc_042_tin-19600.000_tend-24700.000.fits">
      <parameter scale="1e+00" name="Normalization" min="0.0" max="1000.0" free="0" value="1.00000" />
    </temporal>
  </source>
  <source type="PointSource" name="Event616_43" tscalc="1">
    <spectrum type="FileFunction" file="/home/irene/cta/models/afterglow/Event616/spectra/spec_043_tin-24700.000_tend-31300.000.txt">
      <parameter scale="1e+00" name="Normalization" min="1e-7" max="1000" free="1" value="1.00000" />
    </spectrum>
    <spatialModel type="SkyDirFunction">
      <parameter scale="1.0" name="RA" min="-360" max="360" free="0" value="0" />
      <parameter scale="1.0" name="DEC" min="-90" max="90" free="0" value="0.75" />
    </spatialModel>
    <temporal type="LightCurve" file="/home/irene/cta/models/afterglow/Event616/lightcv/lc_043_tin-24700.000_tend-31300.000.fits">
      <parameter scale="1e+00" name="Normalization" min="0.0" max="1000.0" free="0" value="1.00000" />
    </temporal>
  </source>
  <source type="PointSource" name="Event616_44" tscalc="1">
    <spectrum type="FileFunction" file="/home/irene/cta/models/afterglow/Event616/spectra/spec_044_tin-31300.000_tend-40100.000.txt">
      <parameter scale="1e+00" name="Normalization" min="1e-7" max="1000" free="1" value="1.00000" />
    </spectrum>
    <spatialModel type="SkyDirFunction">
      <parameter scale="1.0" name="RA" min="-360" max="360" free="0" value="0" />
      <parameter scale="1.0" name="DEC" min="-90" max="90" free="0" value="0.75" />
    </spatialModel>
    <temporal type="LightCurve" file="/home/irene/cta/models/afterglow/Event616/lightcv/lc_044_tin-31300.000_tend-40100.000.fits">
      <parameter scale="1e+00" name="Normalization" min="0.0" max="1000.0" free="0" value="1.00000" />
    </temporal>
  </source>
  <source type="PointSource" name="Event616_45" tscalc="1">
    <spectrum type="FileFunction" file="/home/irene/cta/models/afterglow/Event616/spectra/spec_045_tin-40100.000_tend-51600.000.txt">
      <parameter scale="1e+00" name="Normalization" min="1e-7" max="1000" free="1" value="1.00000" />
    </spectrum>
    <spatialModel type="SkyDirFunction">
      <parameter scale="1.0" name="RA" min="-360" max="360" free="0" value="0" />
      <parameter scale="1.0" name="DEC" min="-90" max="90" free="0" value="0.75" />
    </spatialModel>
    <temporal type="LightCurve" file="/home/irene/cta/models/afterglow/Event616/lightcv/lc_045_tin-40100.000_tend-51600.000.fits">
      <parameter scale="1e+00" name="Normalization" min="0.0" max="1000.0" free="0" value="1.00000" />
    </temporal>
  </source>
  <source type="PointSource" name="Event616_46" tscalc="1">
    <spectrum type="FileFunction" file="/home/irene/cta/models/afterglow/Event616/spectra/spec_046_tin-51600.000_tend-64900.000.txt">
      <parameter scale="1e+00" name="Normalization" min="1e-7" max="1000" free="1" value="1.00000" />
    </spectrum>
    <spatialModel type="SkyDirFunction">
      <parameter scale="1.0" name="RA" min="-360" max="360" free="0" value="0" />
      <parameter scale="1.0" name="DEC" min="-90" max="90" free="0" value="0.75" />
    </spatialModel>
    <temporal type="LightCurve" file="/home/irene/cta/models/afterglow/Event616/lightcv/lc_046_tin-51600.000_tend-64900.000.fits">
      <parameter scale="1e+00" name="Normalization" min="0.0" max="1000.0" free="0" value="1.00000" />
    </temporal>
  </source>
  <source type="PointSource" name="Event616_47" tscalc="1">
    <spectrum type="FileFunction" file="/home/irene/cta/models/afterglow/Event616/spectra/spec_047_tin-64900.000_tend-82200.000.txt">
      <parameter scale="1e+00" name="Normalization" min="1e-7" max="1000" free="1" value="1.00000" />
    </spectrum>
    <spatialModel type="SkyDirFunction">
      <parameter scale="1.0" name="RA" min="-360" max="360" free="0" value="0" />
      <parameter scale="1.0" name="DEC" min="-90" max="90" free="0" value="0.75" />
    </spatialModel>
    <temporal type="LightCurve" file="/home/irene/cta/models/afterglow/Event616/lightcv/lc_047_tin-64900.000_tend-82200.000.fits">
      <parameter scale="1e+00" name="Normalization" min="0.0" max="1000.0" free="0" value="1.00000" />
    </temporal>
  </source>
  <source type="PointSource" name="Event616_48" tscalc="1">
    <spectrum type="FileFunction" file="/home/irene/cta/models/afterglow/Event616/spectra/spec_048_tin-82200.000_tend-105000.000.txt">
      <parameter scale="1e+00" name="Normalization" min="1e-7" max="1000" free="1" value="1.00000" />
    </spectrum>
    <spatialModel type="SkyDirFunction">
      <parameter scale="1.0" name="RA" min="-360" max="360" free="0" value="0" />
      <parameter scale="1.0" name="DEC" min="-90" max="90" free="0" value="0.75" />
    </spatialModel>
    <temporal type="LightCurve" file="/home/irene/cta/models/afterglow/Event616/lightcv/lc_048_tin-82200.000_tend-105000.000.fits">
      <parameter scale="1e+00" name="Normalization" min="0.0" max="1000.0" free="0" value="1.00000" />
    </temporal>
  </source>
  <source type="PointSource" name="Event616_49" tscalc="1">
    <spectrum type="FileFunction" file="/home/irene/cta/models/afterglow/Event616/spectra/spec_049_tin-105000.000_tend-134000.000.txt">
      <parameter scale="1e+00" name="Normalization" min="1e-7" max="1000" free="1" value="1.00000" />
    </spectrum>
    <spatialModel type="SkyDirFunction">
      <parameter scale="1.0" name="RA" min="-360" max="360" free="0" value="0" />
      <parameter scale="1.0" name="DEC" min="-90" max="90" free="0" value="0.75" />
    </spatialModel>
    <temporal type="LightCurve" file="/home/irene/cta/models/afterglow/Event616/lightcv/lc_049_tin-105000.000_tend-134000.000.fits">
      <parameter scale="1e+00" name="Normalization" min="0.0" max="1000.0" free="0" value="1.00000" />
    </temporal>
  </source>
  <source type="PointSource" name="Event616_50" tscalc="1">
    <spectrum type="FileFunction" file="/home/irene/cta/models/afterglow/Event616/spectra/spec_050_tin-134000.000_tend-174000.000.txt">
      <parameter scale="1e+00" name="Normalization" min="1e-7" max="1000" free="1" value="1.00000" />
    </spectrum>
    <spatialModel type="SkyDirFunction">
      <parameter scale="1.0" name="RA" min="-360" max="360" free="0" value="0" />
      <parameter scale="1.0" name="DEC" min="-90" max="90" free="0" value="0.75" />
    </spatialModel>
    <temporal type="LightCurve" file="/home/irene/cta/models/afterglow/Event616/lightcv/lc_050_tin-134000.000_tend-174000.000.fits">
      <parameter scale="1e+00" name="Normalization" min="0.0" max="1000.0" free="0" value="1.00000" />
    </temporal>
  </source>
</source_library>
