<?xml version="1.0" encoding="UTF-8" standalone="no"?>
<source_library title="source library">
  <source name="Background" type="CTAIrfBackground" instrument="CTA">
    <spectrum type="PowerLaw">
      <parameter scale="1e+00" name="Prefactor" min="1e-7" max="1000" free="1" value="1.00000" />
      <parameter scale="-1.0" name="Index" min="0.0" max="+10.0" free="1" value="0.0" />
      <parameter scale="1.0" name="Scale" min="0.0" max="+10000000.0" free="0" value="300000.0" />
    </spectrum>
  </source>
  <source type="PointSource" name="Event913_0" tscalc="1">
    <spectrum type="FileFunction" file="/home/irene/cta/models/afterglow/Event913/spectra/spec_000_tin-0.996_tend-1.250.txt">
      <parameter scale="1e+00" name="Normalization" min="1e-7" max="1000" free="1" value="1.00000" />
    </spectrum>
    <spatialModel type="SkyDirFunction">
      <parameter scale="1.0" name="RA" min="-360" max="360" free="0" value="0" />
      <parameter scale="1.0" name="DEC" min="-90" max="90" free="0" value="0.75" />
    </spatialModel>
    <temporal type="LightCurve" file="/home/irene/cta/models/afterglow/Event913/lightcv/lc_000_tin-0.996_tend-1.250.fits">
      <parameter scale="1e+00" name="Normalization" min="0.0" max="1000.0" free="0" value="1.00000" />
    </temporal>
  </source>
  <source type="PointSource" name="Event913_1" tscalc="1">
    <spectrum type="FileFunction" file="/home/irene/cta/models/afterglow/Event913/spectra/spec_001_tin-1.250_tend-1.560.txt">
      <parameter scale="1e+00" name="Normalization" min="1e-7" max="1000" free="1" value="1.00000" />
    </spectrum>
    <spatialModel type="SkyDirFunction">
      <parameter scale="1.0" name="RA" min="-360" max="360" free="0" value="0" />
      <parameter scale="1.0" name="DEC" min="-90" max="90" free="0" value="0.75" />
    </spatialModel>
    <temporal type="LightCurve" file="/home/irene/cta/models/afterglow/Event913/lightcv/lc_001_tin-1.250_tend-1.560.fits">
      <parameter scale="1e+00" name="Normalization" min="0.0" max="1000.0" free="0" value="1.00000" />
    </temporal>
  </source>
  <source type="PointSource" name="Event913_2" tscalc="1">
    <spectrum type="FileFunction" file="/home/irene/cta/models/afterglow/Event913/spectra/spec_002_tin-1.560_tend-1.960.txt">
      <parameter scale="1e+00" name="Normalization" min="1e-7" max="1000" free="1" value="1.00000" />
    </spectrum>
    <spatialModel type="SkyDirFunction">
      <parameter scale="1.0" name="RA" min="-360" max="360" free="0" value="0" />
      <parameter scale="1.0" name="DEC" min="-90" max="90" free="0" value="0.75" />
    </spatialModel>
    <temporal type="LightCurve" file="/home/irene/cta/models/afterglow/Event913/lightcv/lc_002_tin-1.560_tend-1.960.fits">
      <parameter scale="1e+00" name="Normalization" min="0.0" max="1000.0" free="0" value="1.00000" />
    </temporal>
  </source>
  <source type="PointSource" name="Event913_3" tscalc="1">
    <spectrum type="FileFunction" file="/home/irene/cta/models/afterglow/Event913/spectra/spec_003_tin-1.960_tend-2.450.txt">
      <parameter scale="1e+00" name="Normalization" min="1e-7" max="1000" free="1" value="1.00000" />
    </spectrum>
    <spatialModel type="SkyDirFunction">
      <parameter scale="1.0" name="RA" min="-360" max="360" free="0" value="0" />
      <parameter scale="1.0" name="DEC" min="-90" max="90" free="0" value="0.75" />
    </spatialModel>
    <temporal type="LightCurve" file="/home/irene/cta/models/afterglow/Event913/lightcv/lc_003_tin-1.960_tend-2.450.fits">
      <parameter scale="1e+00" name="Normalization" min="0.0" max="1000.0" free="0" value="1.00000" />
    </temporal>
  </source>
  <source type="PointSource" name="Event913_4" tscalc="1">
    <spectrum type="FileFunction" file="/home/irene/cta/models/afterglow/Event913/spectra/spec_004_tin-2.450_tend-3.070.txt">
      <parameter scale="1e+00" name="Normalization" min="1e-7" max="1000" free="1" value="1.00000" />
    </spectrum>
    <spatialModel type="SkyDirFunction">
      <parameter scale="1.0" name="RA" min="-360" max="360" free="0" value="0" />
      <parameter scale="1.0" name="DEC" min="-90" max="90" free="0" value="0.75" />
    </spatialModel>
    <temporal type="LightCurve" file="/home/irene/cta/models/afterglow/Event913/lightcv/lc_004_tin-2.450_tend-3.070.fits">
      <parameter scale="1e+00" name="Normalization" min="0.0" max="1000.0" free="0" value="1.00000" />
    </temporal>
  </source>
  <source type="PointSource" name="Event913_5" tscalc="1">
    <spectrum type="FileFunction" file="/home/irene/cta/models/afterglow/Event913/spectra/spec_005_tin-3.070_tend-3.840.txt">
      <parameter scale="1e+00" name="Normalization" min="1e-7" max="1000" free="1" value="1.00000" />
    </spectrum>
    <spatialModel type="SkyDirFunction">
      <parameter scale="1.0" name="RA" min="-360" max="360" free="0" value="0" />
      <parameter scale="1.0" name="DEC" min="-90" max="90" free="0" value="0.75" />
    </spatialModel>
    <temporal type="LightCurve" file="/home/irene/cta/models/afterglow/Event913/lightcv/lc_005_tin-3.070_tend-3.840.fits">
      <parameter scale="1e+00" name="Normalization" min="0.0" max="1000.0" free="0" value="1.00000" />
    </temporal>
  </source>
  <source type="PointSource" name="Event913_6" tscalc="1">
    <spectrum type="FileFunction" file="/home/irene/cta/models/afterglow/Event913/spectra/spec_006_tin-3.840_tend-4.800.txt">
      <parameter scale="1e+00" name="Normalization" min="1e-7" max="1000" free="1" value="1.00000" />
    </spectrum>
    <spatialModel type="SkyDirFunction">
      <parameter scale="1.0" name="RA" min="-360" max="360" free="0" value="0" />
      <parameter scale="1.0" name="DEC" min="-90" max="90" free="0" value="0.75" />
    </spatialModel>
    <temporal type="LightCurve" file="/home/irene/cta/models/afterglow/Event913/lightcv/lc_006_tin-3.840_tend-4.800.fits">
      <parameter scale="1e+00" name="Normalization" min="0.0" max="1000.0" free="0" value="1.00000" />
    </temporal>
  </source>
  <source type="PointSource" name="Event913_7" tscalc="1">
    <spectrum type="FileFunction" file="/home/irene/cta/models/afterglow/Event913/spectra/spec_007_tin-4.800_tend-6.010.txt">
      <parameter scale="1e+00" name="Normalization" min="1e-7" max="1000" free="1" value="1.00000" />
    </spectrum>
    <spatialModel type="SkyDirFunction">
      <parameter scale="1.0" name="RA" min="-360" max="360" free="0" value="0" />
      <parameter scale="1.0" name="DEC" min="-90" max="90" free="0" value="0.75" />
    </spatialModel>
    <temporal type="LightCurve" file="/home/irene/cta/models/afterglow/Event913/lightcv/lc_007_tin-4.800_tend-6.010.fits">
      <parameter scale="1e+00" name="Normalization" min="0.0" max="1000.0" free="0" value="1.00000" />
    </temporal>
  </source>
  <source type="PointSource" name="Event913_8" tscalc="1">
    <spectrum type="FileFunction" file="/home/irene/cta/models/afterglow/Event913/spectra/spec_008_tin-6.010_tend-7.510.txt">
      <parameter scale="1e+00" name="Normalization" min="1e-7" max="1000" free="1" value="1.00000" />
    </spectrum>
    <spatialModel type="SkyDirFunction">
      <parameter scale="1.0" name="RA" min="-360" max="360" free="0" value="0" />
      <parameter scale="1.0" name="DEC" min="-90" max="90" free="0" value="0.75" />
    </spatialModel>
    <temporal type="LightCurve" file="/home/irene/cta/models/afterglow/Event913/lightcv/lc_008_tin-6.010_tend-7.510.fits">
      <parameter scale="1e+00" name="Normalization" min="0.0" max="1000.0" free="0" value="1.00000" />
    </temporal>
  </source>
  <source type="PointSource" name="Event913_9" tscalc="1">
    <spectrum type="FileFunction" file="/home/irene/cta/models/afterglow/Event913/spectra/spec_009_tin-7.510_tend-9.400.txt">
      <parameter scale="1e+00" name="Normalization" min="1e-7" max="1000" free="1" value="1.00000" />
    </spectrum>
    <spatialModel type="SkyDirFunction">
      <parameter scale="1.0" name="RA" min="-360" max="360" free="0" value="0" />
      <parameter scale="1.0" name="DEC" min="-90" max="90" free="0" value="0.75" />
    </spatialModel>
    <temporal type="LightCurve" file="/home/irene/cta/models/afterglow/Event913/lightcv/lc_009_tin-7.510_tend-9.400.fits">
      <parameter scale="1e+00" name="Normalization" min="0.0" max="1000.0" free="0" value="1.00000" />
    </temporal>
  </source>
  <source type="PointSource" name="Event913_10" tscalc="1">
    <spectrum type="FileFunction" file="/home/irene/cta/models/afterglow/Event913/spectra/spec_010_tin-9.400_tend-11.700.txt">
      <parameter scale="1e+00" name="Normalization" min="1e-7" max="1000" free="1" value="1.00000" />
    </spectrum>
    <spatialModel type="SkyDirFunction">
      <parameter scale="1.0" name="RA" min="-360" max="360" free="0" value="0" />
      <parameter scale="1.0" name="DEC" min="-90" max="90" free="0" value="0.75" />
    </spatialModel>
    <temporal type="LightCurve" file="/home/irene/cta/models/afterglow/Event913/lightcv/lc_010_tin-9.400_tend-11.700.fits">
      <parameter scale="1e+00" name="Normalization" min="0.0" max="1000.0" free="0" value="1.00000" />
    </temporal>
  </source>
  <source type="PointSource" name="Event913_11" tscalc="1">
    <spectrum type="FileFunction" file="/home/irene/cta/models/afterglow/Event913/spectra/spec_011_tin-11.700_tend-14.700.txt">
      <parameter scale="1e+00" name="Normalization" min="1e-7" max="1000" free="1" value="1.00000" />
    </spectrum>
    <spatialModel type="SkyDirFunction">
      <parameter scale="1.0" name="RA" min="-360" max="360" free="0" value="0" />
      <parameter scale="1.0" name="DEC" min="-90" max="90" free="0" value="0.75" />
    </spatialModel>
    <temporal type="LightCurve" file="/home/irene/cta/models/afterglow/Event913/lightcv/lc_011_tin-11.700_tend-14.700.fits">
      <parameter scale="1e+00" name="Normalization" min="0.0" max="1000.0" free="0" value="1.00000" />
    </temporal>
  </source>
  <source type="PointSource" name="Event913_12" tscalc="1">
    <spectrum type="FileFunction" file="/home/irene/cta/models/afterglow/Event913/spectra/spec_012_tin-14.700_tend-18.400.txt">
      <parameter scale="1e+00" name="Normalization" min="1e-7" max="1000" free="1" value="1.00000" />
    </spectrum>
    <spatialModel type="SkyDirFunction">
      <parameter scale="1.0" name="RA" min="-360" max="360" free="0" value="0" />
      <parameter scale="1.0" name="DEC" min="-90" max="90" free="0" value="0.75" />
    </spatialModel>
    <temporal type="LightCurve" file="/home/irene/cta/models/afterglow/Event913/lightcv/lc_012_tin-14.700_tend-18.400.fits">
      <parameter scale="1e+00" name="Normalization" min="0.0" max="1000.0" free="0" value="1.00000" />
    </temporal>
  </source>
  <source type="PointSource" name="Event913_13" tscalc="1">
    <spectrum type="FileFunction" file="/home/irene/cta/models/afterglow/Event913/spectra/spec_013_tin-18.400_tend-23.000.txt">
      <parameter scale="1e+00" name="Normalization" min="1e-7" max="1000" free="1" value="1.00000" />
    </spectrum>
    <spatialModel type="SkyDirFunction">
      <parameter scale="1.0" name="RA" min="-360" max="360" free="0" value="0" />
      <parameter scale="1.0" name="DEC" min="-90" max="90" free="0" value="0.75" />
    </spatialModel>
    <temporal type="LightCurve" file="/home/irene/cta/models/afterglow/Event913/lightcv/lc_013_tin-18.400_tend-23.000.fits">
      <parameter scale="1e+00" name="Normalization" min="0.0" max="1000.0" free="0" value="1.00000" />
    </temporal>
  </source>
  <source type="PointSource" name="Event913_14" tscalc="1">
    <spectrum type="FileFunction" file="/home/irene/cta/models/afterglow/Event913/spectra/spec_014_tin-23.000_tend-28.700.txt">
      <parameter scale="1e+00" name="Normalization" min="1e-7" max="1000" free="1" value="1.00000" />
    </spectrum>
    <spatialModel type="SkyDirFunction">
      <parameter scale="1.0" name="RA" min="-360" max="360" free="0" value="0" />
      <parameter scale="1.0" name="DEC" min="-90" max="90" free="0" value="0.75" />
    </spatialModel>
    <temporal type="LightCurve" file="/home/irene/cta/models/afterglow/Event913/lightcv/lc_014_tin-23.000_tend-28.700.fits">
      <parameter scale="1e+00" name="Normalization" min="0.0" max="1000.0" free="0" value="1.00000" />
    </temporal>
  </source>
  <source type="PointSource" name="Event913_15" tscalc="1">
    <spectrum type="FileFunction" file="/home/irene/cta/models/afterglow/Event913/spectra/spec_015_tin-28.700_tend-35.900.txt">
      <parameter scale="1e+00" name="Normalization" min="1e-7" max="1000" free="1" value="1.00000" />
    </spectrum>
    <spatialModel type="SkyDirFunction">
      <parameter scale="1.0" name="RA" min="-360" max="360" free="0" value="0" />
      <parameter scale="1.0" name="DEC" min="-90" max="90" free="0" value="0.75" />
    </spatialModel>
    <temporal type="LightCurve" file="/home/irene/cta/models/afterglow/Event913/lightcv/lc_015_tin-28.700_tend-35.900.fits">
      <parameter scale="1e+00" name="Normalization" min="0.0" max="1000.0" free="0" value="1.00000" />
    </temporal>
  </source>
  <source type="PointSource" name="Event913_16" tscalc="1">
    <spectrum type="FileFunction" file="/home/irene/cta/models/afterglow/Event913/spectra/spec_016_tin-35.900_tend-45.000.txt">
      <parameter scale="1e+00" name="Normalization" min="1e-7" max="1000" free="1" value="1.00000" />
    </spectrum>
    <spatialModel type="SkyDirFunction">
      <parameter scale="1.0" name="RA" min="-360" max="360" free="0" value="0" />
      <parameter scale="1.0" name="DEC" min="-90" max="90" free="0" value="0.75" />
    </spatialModel>
    <temporal type="LightCurve" file="/home/irene/cta/models/afterglow/Event913/lightcv/lc_016_tin-35.900_tend-45.000.fits">
      <parameter scale="1e+00" name="Normalization" min="0.0" max="1000.0" free="0" value="1.00000" />
    </temporal>
  </source>
  <source type="PointSource" name="Event913_17" tscalc="1">
    <spectrum type="FileFunction" file="/home/irene/cta/models/afterglow/Event913/spectra/spec_017_tin-45.000_tend-56.300.txt">
      <parameter scale="1e+00" name="Normalization" min="1e-7" max="1000" free="1" value="1.00000" />
    </spectrum>
    <spatialModel type="SkyDirFunction">
      <parameter scale="1.0" name="RA" min="-360" max="360" free="0" value="0" />
      <parameter scale="1.0" name="DEC" min="-90" max="90" free="0" value="0.75" />
    </spatialModel>
    <temporal type="LightCurve" file="/home/irene/cta/models/afterglow/Event913/lightcv/lc_017_tin-45.000_tend-56.300.fits">
      <parameter scale="1e+00" name="Normalization" min="0.0" max="1000.0" free="0" value="1.00000" />
    </temporal>
  </source>
  <source type="PointSource" name="Event913_18" tscalc="1">
    <spectrum type="FileFunction" file="/home/irene/cta/models/afterglow/Event913/spectra/spec_018_tin-56.300_tend-70.400.txt">
      <parameter scale="1e+00" name="Normalization" min="1e-7" max="1000" free="1" value="1.00000" />
    </spectrum>
    <spatialModel type="SkyDirFunction">
      <parameter scale="1.0" name="RA" min="-360" max="360" free="0" value="0" />
      <parameter scale="1.0" name="DEC" min="-90" max="90" free="0" value="0.75" />
    </spatialModel>
    <temporal type="LightCurve" file="/home/irene/cta/models/afterglow/Event913/lightcv/lc_018_tin-56.300_tend-70.400.fits">
      <parameter scale="1e+00" name="Normalization" min="0.0" max="1000.0" free="0" value="1.00000" />
    </temporal>
  </source>
  <source type="PointSource" name="Event913_19" tscalc="1">
    <spectrum type="FileFunction" file="/home/irene/cta/models/afterglow/Event913/spectra/spec_019_tin-70.400_tend-88.200.txt">
      <parameter scale="1e+00" name="Normalization" min="1e-7" max="1000" free="1" value="1.00000" />
    </spectrum>
    <spatialModel type="SkyDirFunction">
      <parameter scale="1.0" name="RA" min="-360" max="360" free="0" value="0" />
      <parameter scale="1.0" name="DEC" min="-90" max="90" free="0" value="0.75" />
    </spatialModel>
    <temporal type="LightCurve" file="/home/irene/cta/models/afterglow/Event913/lightcv/lc_019_tin-70.400_tend-88.200.fits">
      <parameter scale="1e+00" name="Normalization" min="0.0" max="1000.0" free="0" value="1.00000" />
    </temporal>
  </source>
  <source type="PointSource" name="Event913_20" tscalc="1">
    <spectrum type="FileFunction" file="/home/irene/cta/models/afterglow/Event913/spectra/spec_020_tin-88.200_tend-110.000.txt">
      <parameter scale="1e+00" name="Normalization" min="1e-7" max="1000" free="1" value="1.00000" />
    </spectrum>
    <spatialModel type="SkyDirFunction">
      <parameter scale="1.0" name="RA" min="-360" max="360" free="0" value="0" />
      <parameter scale="1.0" name="DEC" min="-90" max="90" free="0" value="0.75" />
    </spatialModel>
    <temporal type="LightCurve" file="/home/irene/cta/models/afterglow/Event913/lightcv/lc_020_tin-88.200_tend-110.000.fits">
      <parameter scale="1e+00" name="Normalization" min="0.0" max="1000.0" free="0" value="1.00000" />
    </temporal>
  </source>
  <source type="PointSource" name="Event913_21" tscalc="1">
    <spectrum type="FileFunction" file="/home/irene/cta/models/afterglow/Event913/spectra/spec_021_tin-110.000_tend-138.000.txt">
      <parameter scale="1e+00" name="Normalization" min="1e-7" max="1000" free="1" value="1.00000" />
    </spectrum>
    <spatialModel type="SkyDirFunction">
      <parameter scale="1.0" name="RA" min="-360" max="360" free="0" value="0" />
      <parameter scale="1.0" name="DEC" min="-90" max="90" free="0" value="0.75" />
    </spatialModel>
    <temporal type="LightCurve" file="/home/irene/cta/models/afterglow/Event913/lightcv/lc_021_tin-110.000_tend-138.000.fits">
      <parameter scale="1e+00" name="Normalization" min="0.0" max="1000.0" free="0" value="1.00000" />
    </temporal>
  </source>
  <source type="PointSource" name="Event913_22" tscalc="1">
    <spectrum type="FileFunction" file="/home/irene/cta/models/afterglow/Event913/spectra/spec_022_tin-138.000_tend-172.000.txt">
      <parameter scale="1e+00" name="Normalization" min="1e-7" max="1000" free="1" value="1.00000" />
    </spectrum>
    <spatialModel type="SkyDirFunction">
      <parameter scale="1.0" name="RA" min="-360" max="360" free="0" value="0" />
      <parameter scale="1.0" name="DEC" min="-90" max="90" free="0" value="0.75" />
    </spatialModel>
    <temporal type="LightCurve" file="/home/irene/cta/models/afterglow/Event913/lightcv/lc_022_tin-138.000_tend-172.000.fits">
      <parameter scale="1e+00" name="Normalization" min="0.0" max="1000.0" free="0" value="1.00000" />
    </temporal>
  </source>
  <source type="PointSource" name="Event913_23" tscalc="1">
    <spectrum type="FileFunction" file="/home/irene/cta/models/afterglow/Event913/spectra/spec_023_tin-172.000_tend-216.000.txt">
      <parameter scale="1e+00" name="Normalization" min="1e-7" max="1000" free="1" value="1.00000" />
    </spectrum>
    <spatialModel type="SkyDirFunction">
      <parameter scale="1.0" name="RA" min="-360" max="360" free="0" value="0" />
      <parameter scale="1.0" name="DEC" min="-90" max="90" free="0" value="0.75" />
    </spatialModel>
    <temporal type="LightCurve" file="/home/irene/cta/models/afterglow/Event913/lightcv/lc_023_tin-172.000_tend-216.000.fits">
      <parameter scale="1e+00" name="Normalization" min="0.0" max="1000.0" free="0" value="1.00000" />
    </temporal>
  </source>
  <source type="PointSource" name="Event913_24" tscalc="1">
    <spectrum type="FileFunction" file="/home/irene/cta/models/afterglow/Event913/spectra/spec_024_tin-216.000_tend-270.000.txt">
      <parameter scale="1e+00" name="Normalization" min="1e-7" max="1000" free="1" value="1.00000" />
    </spectrum>
    <spatialModel type="SkyDirFunction">
      <parameter scale="1.0" name="RA" min="-360" max="360" free="0" value="0" />
      <parameter scale="1.0" name="DEC" min="-90" max="90" free="0" value="0.75" />
    </spatialModel>
    <temporal type="LightCurve" file="/home/irene/cta/models/afterglow/Event913/lightcv/lc_024_tin-216.000_tend-270.000.fits">
      <parameter scale="1e+00" name="Normalization" min="0.0" max="1000.0" free="0" value="1.00000" />
    </temporal>
  </source>
  <source type="PointSource" name="Event913_25" tscalc="1">
    <spectrum type="FileFunction" file="/home/irene/cta/models/afterglow/Event913/spectra/spec_025_tin-270.000_tend-338.000.txt">
      <parameter scale="1e+00" name="Normalization" min="1e-7" max="1000" free="1" value="1.00000" />
    </spectrum>
    <spatialModel type="SkyDirFunction">
      <parameter scale="1.0" name="RA" min="-360" max="360" free="0" value="0" />
      <parameter scale="1.0" name="DEC" min="-90" max="90" free="0" value="0.75" />
    </spatialModel>
    <temporal type="LightCurve" file="/home/irene/cta/models/afterglow/Event913/lightcv/lc_025_tin-270.000_tend-338.000.fits">
      <parameter scale="1e+00" name="Normalization" min="0.0" max="1000.0" free="0" value="1.00000" />
    </temporal>
  </source>
  <source type="PointSource" name="Event913_26" tscalc="1">
    <spectrum type="FileFunction" file="/home/irene/cta/models/afterglow/Event913/spectra/spec_026_tin-338.000_tend-423.000.txt">
      <parameter scale="1e+00" name="Normalization" min="1e-7" max="1000" free="1" value="1.00000" />
    </spectrum>
    <spatialModel type="SkyDirFunction">
      <parameter scale="1.0" name="RA" min="-360" max="360" free="0" value="0" />
      <parameter scale="1.0" name="DEC" min="-90" max="90" free="0" value="0.75" />
    </spatialModel>
    <temporal type="LightCurve" file="/home/irene/cta/models/afterglow/Event913/lightcv/lc_026_tin-338.000_tend-423.000.fits">
      <parameter scale="1e+00" name="Normalization" min="0.0" max="1000.0" free="0" value="1.00000" />
    </temporal>
  </source>
  <source type="PointSource" name="Event913_27" tscalc="1">
    <spectrum type="FileFunction" file="/home/irene/cta/models/afterglow/Event913/spectra/spec_027_tin-423.000_tend-529.000.txt">
      <parameter scale="1e+00" name="Normalization" min="1e-7" max="1000" free="1" value="1.00000" />
    </spectrum>
    <spatialModel type="SkyDirFunction">
      <parameter scale="1.0" name="RA" min="-360" max="360" free="0" value="0" />
      <parameter scale="1.0" name="DEC" min="-90" max="90" free="0" value="0.75" />
    </spatialModel>
    <temporal type="LightCurve" file="/home/irene/cta/models/afterglow/Event913/lightcv/lc_027_tin-423.000_tend-529.000.fits">
      <parameter scale="1e+00" name="Normalization" min="0.0" max="1000.0" free="0" value="1.00000" />
    </temporal>
  </source>
  <source type="PointSource" name="Event913_28" tscalc="1">
    <spectrum type="FileFunction" file="/home/irene/cta/models/afterglow/Event913/spectra/spec_028_tin-529.000_tend-662.000.txt">
      <parameter scale="1e+00" name="Normalization" min="1e-7" max="1000" free="1" value="1.00000" />
    </spectrum>
    <spatialModel type="SkyDirFunction">
      <parameter scale="1.0" name="RA" min="-360" max="360" free="0" value="0" />
      <parameter scale="1.0" name="DEC" min="-90" max="90" free="0" value="0.75" />
    </spatialModel>
    <temporal type="LightCurve" file="/home/irene/cta/models/afterglow/Event913/lightcv/lc_028_tin-529.000_tend-662.000.fits">
      <parameter scale="1e+00" name="Normalization" min="0.0" max="1000.0" free="0" value="1.00000" />
    </temporal>
  </source>
  <source type="PointSource" name="Event913_29" tscalc="1">
    <spectrum type="FileFunction" file="/home/irene/cta/models/afterglow/Event913/spectra/spec_029_tin-662.000_tend-830.000.txt">
      <parameter scale="1e+00" name="Normalization" min="1e-7" max="1000" free="1" value="1.00000" />
    </spectrum>
    <spatialModel type="SkyDirFunction">
      <parameter scale="1.0" name="RA" min="-360" max="360" free="0" value="0" />
      <parameter scale="1.0" name="DEC" min="-90" max="90" free="0" value="0.75" />
    </spatialModel>
    <temporal type="LightCurve" file="/home/irene/cta/models/afterglow/Event913/lightcv/lc_029_tin-662.000_tend-830.000.fits">
      <parameter scale="1e+00" name="Normalization" min="0.0" max="1000.0" free="0" value="1.00000" />
    </temporal>
  </source>
  <source type="PointSource" name="Event913_30" tscalc="1">
    <spectrum type="FileFunction" file="/home/irene/cta/models/afterglow/Event913/spectra/spec_030_tin-830.000_tend-1040.000.txt">
      <parameter scale="1e+00" name="Normalization" min="1e-7" max="1000" free="1" value="1.00000" />
    </spectrum>
    <spatialModel type="SkyDirFunction">
      <parameter scale="1.0" name="RA" min="-360" max="360" free="0" value="0" />
      <parameter scale="1.0" name="DEC" min="-90" max="90" free="0" value="0.75" />
    </spatialModel>
    <temporal type="LightCurve" file="/home/irene/cta/models/afterglow/Event913/lightcv/lc_030_tin-830.000_tend-1040.000.fits">
      <parameter scale="1e+00" name="Normalization" min="0.0" max="1000.0" free="0" value="1.00000" />
    </temporal>
  </source>
  <source type="PointSource" name="Event913_31" tscalc="1">
    <spectrum type="FileFunction" file="/home/irene/cta/models/afterglow/Event913/spectra/spec_031_tin-1040.000_tend-1300.000.txt">
      <parameter scale="1e+00" name="Normalization" min="1e-7" max="1000" free="1" value="1.00000" />
    </spectrum>
    <spatialModel type="SkyDirFunction">
      <parameter scale="1.0" name="RA" min="-360" max="360" free="0" value="0" />
      <parameter scale="1.0" name="DEC" min="-90" max="90" free="0" value="0.75" />
    </spatialModel>
    <temporal type="LightCurve" file="/home/irene/cta/models/afterglow/Event913/lightcv/lc_031_tin-1040.000_tend-1300.000.fits">
      <parameter scale="1e+00" name="Normalization" min="0.0" max="1000.0" free="0" value="1.00000" />
    </temporal>
  </source>
  <source type="PointSource" name="Event913_32" tscalc="1">
    <spectrum type="FileFunction" file="/home/irene/cta/models/afterglow/Event913/spectra/spec_032_tin-1300.000_tend-1630.000.txt">
      <parameter scale="1e+00" name="Normalization" min="1e-7" max="1000" free="1" value="1.00000" />
    </spectrum>
    <spatialModel type="SkyDirFunction">
      <parameter scale="1.0" name="RA" min="-360" max="360" free="0" value="0" />
      <parameter scale="1.0" name="DEC" min="-90" max="90" free="0" value="0.75" />
    </spatialModel>
    <temporal type="LightCurve" file="/home/irene/cta/models/afterglow/Event913/lightcv/lc_032_tin-1300.000_tend-1630.000.fits">
      <parameter scale="1e+00" name="Normalization" min="0.0" max="1000.0" free="0" value="1.00000" />
    </temporal>
  </source>
  <source type="PointSource" name="Event913_33" tscalc="1">
    <spectrum type="FileFunction" file="/home/irene/cta/models/afterglow/Event913/spectra/spec_033_tin-1630.000_tend-2040.000.txt">
      <parameter scale="1e+00" name="Normalization" min="1e-7" max="1000" free="1" value="1.00000" />
    </spectrum>
    <spatialModel type="SkyDirFunction">
      <parameter scale="1.0" name="RA" min="-360" max="360" free="0" value="0" />
      <parameter scale="1.0" name="DEC" min="-90" max="90" free="0" value="0.75" />
    </spatialModel>
    <temporal type="LightCurve" file="/home/irene/cta/models/afterglow/Event913/lightcv/lc_033_tin-1630.000_tend-2040.000.fits">
      <parameter scale="1e+00" name="Normalization" min="0.0" max="1000.0" free="0" value="1.00000" />
    </temporal>
  </source>
  <source type="PointSource" name="Event913_34" tscalc="1">
    <spectrum type="FileFunction" file="/home/irene/cta/models/afterglow/Event913/spectra/spec_034_tin-2040.000_tend-2560.000.txt">
      <parameter scale="1e+00" name="Normalization" min="1e-7" max="1000" free="1" value="1.00000" />
    </spectrum>
    <spatialModel type="SkyDirFunction">
      <parameter scale="1.0" name="RA" min="-360" max="360" free="0" value="0" />
      <parameter scale="1.0" name="DEC" min="-90" max="90" free="0" value="0.75" />
    </spatialModel>
    <temporal type="LightCurve" file="/home/irene/cta/models/afterglow/Event913/lightcv/lc_034_tin-2040.000_tend-2560.000.fits">
      <parameter scale="1e+00" name="Normalization" min="0.0" max="1000.0" free="0" value="1.00000" />
    </temporal>
  </source>
  <source type="PointSource" name="Event913_35" tscalc="1">
    <spectrum type="FileFunction" file="/home/irene/cta/models/afterglow/Event913/spectra/spec_035_tin-2560.000_tend-3200.000.txt">
      <parameter scale="1e+00" name="Normalization" min="1e-7" max="1000" free="1" value="1.00000" />
    </spectrum>
    <spatialModel type="SkyDirFunction">
      <parameter scale="1.0" name="RA" min="-360" max="360" free="0" value="0" />
      <parameter scale="1.0" name="DEC" min="-90" max="90" free="0" value="0.75" />
    </spatialModel>
    <temporal type="LightCurve" file="/home/irene/cta/models/afterglow/Event913/lightcv/lc_035_tin-2560.000_tend-3200.000.fits">
      <parameter scale="1e+00" name="Normalization" min="0.0" max="1000.0" free="0" value="1.00000" />
    </temporal>
  </source>
  <source type="PointSource" name="Event913_36" tscalc="1">
    <spectrum type="FileFunction" file="/home/irene/cta/models/afterglow/Event913/spectra/spec_036_tin-3200.000_tend-4010.000.txt">
      <parameter scale="1e+00" name="Normalization" min="1e-7" max="1000" free="1" value="1.00000" />
    </spectrum>
    <spatialModel type="SkyDirFunction">
      <parameter scale="1.0" name="RA" min="-360" max="360" free="0" value="0" />
      <parameter scale="1.0" name="DEC" min="-90" max="90" free="0" value="0.75" />
    </spatialModel>
    <temporal type="LightCurve" file="/home/irene/cta/models/afterglow/Event913/lightcv/lc_036_tin-3200.000_tend-4010.000.fits">
      <parameter scale="1e+00" name="Normalization" min="0.0" max="1000.0" free="0" value="1.00000" />
    </temporal>
  </source>
  <source type="PointSource" name="Event913_37" tscalc="1">
    <spectrum type="FileFunction" file="/home/irene/cta/models/afterglow/Event913/spectra/spec_037_tin-4010.000_tend-5030.000.txt">
      <parameter scale="1e+00" name="Normalization" min="1e-7" max="1000" free="1" value="1.00000" />
    </spectrum>
    <spatialModel type="SkyDirFunction">
      <parameter scale="1.0" name="RA" min="-360" max="360" free="0" value="0" />
      <parameter scale="1.0" name="DEC" min="-90" max="90" free="0" value="0.75" />
    </spatialModel>
    <temporal type="LightCurve" file="/home/irene/cta/models/afterglow/Event913/lightcv/lc_037_tin-4010.000_tend-5030.000.fits">
      <parameter scale="1e+00" name="Normalization" min="0.0" max="1000.0" free="0" value="1.00000" />
    </temporal>
  </source>
  <source type="PointSource" name="Event913_38" tscalc="1">
    <spectrum type="FileFunction" file="/home/irene/cta/models/afterglow/Event913/spectra/spec_038_tin-5030.000_tend-6300.000.txt">
      <parameter scale="1e+00" name="Normalization" min="1e-7" max="1000" free="1" value="1.00000" />
    </spectrum>
    <spatialModel type="SkyDirFunction">
      <parameter scale="1.0" name="RA" min="-360" max="360" free="0" value="0" />
      <parameter scale="1.0" name="DEC" min="-90" max="90" free="0" value="0.75" />
    </spatialModel>
    <temporal type="LightCurve" file="/home/irene/cta/models/afterglow/Event913/lightcv/lc_038_tin-5030.000_tend-6300.000.fits">
      <parameter scale="1e+00" name="Normalization" min="0.0" max="1000.0" free="0" value="1.00000" />
    </temporal>
  </source>
  <source type="PointSource" name="Event913_39" tscalc="1">
    <spectrum type="FileFunction" file="/home/irene/cta/models/afterglow/Event913/spectra/spec_039_tin-6300.000_tend-7890.000.txt">
      <parameter scale="1e+00" name="Normalization" min="1e-7" max="1000" free="1" value="1.00000" />
    </spectrum>
    <spatialModel type="SkyDirFunction">
      <parameter scale="1.0" name="RA" min="-360" max="360" free="0" value="0" />
      <parameter scale="1.0" name="DEC" min="-90" max="90" free="0" value="0.75" />
    </spatialModel>
    <temporal type="LightCurve" file="/home/irene/cta/models/afterglow/Event913/lightcv/lc_039_tin-6300.000_tend-7890.000.fits">
      <parameter scale="1e+00" name="Normalization" min="0.0" max="1000.0" free="0" value="1.00000" />
    </temporal>
  </source>
  <source type="PointSource" name="Event913_40" tscalc="1">
    <spectrum type="FileFunction" file="/home/irene/cta/models/afterglow/Event913/spectra/spec_040_tin-7890.000_tend-9870.000.txt">
      <parameter scale="1e+00" name="Normalization" min="1e-7" max="1000" free="1" value="1.00000" />
    </spectrum>
    <spatialModel type="SkyDirFunction">
      <parameter scale="1.0" name="RA" min="-360" max="360" free="0" value="0" />
      <parameter scale="1.0" name="DEC" min="-90" max="90" free="0" value="0.75" />
    </spatialModel>
    <temporal type="LightCurve" file="/home/irene/cta/models/afterglow/Event913/lightcv/lc_040_tin-7890.000_tend-9870.000.fits">
      <parameter scale="1e+00" name="Normalization" min="0.0" max="1000.0" free="0" value="1.00000" />
    </temporal>
  </source>
  <source type="PointSource" name="Event913_41" tscalc="1">
    <spectrum type="FileFunction" file="/home/irene/cta/models/afterglow/Event913/spectra/spec_041_tin-9870.000_tend-12300.000.txt">
      <parameter scale="1e+00" name="Normalization" min="1e-7" max="1000" free="1" value="1.00000" />
    </spectrum>
    <spatialModel type="SkyDirFunction">
      <parameter scale="1.0" name="RA" min="-360" max="360" free="0" value="0" />
      <parameter scale="1.0" name="DEC" min="-90" max="90" free="0" value="0.75" />
    </spatialModel>
    <temporal type="LightCurve" file="/home/irene/cta/models/afterglow/Event913/lightcv/lc_041_tin-9870.000_tend-12300.000.fits">
      <parameter scale="1e+00" name="Normalization" min="0.0" max="1000.0" free="0" value="1.00000" />
    </temporal>
  </source>
  <source type="PointSource" name="Event913_42" tscalc="1">
    <spectrum type="FileFunction" file="/home/irene/cta/models/afterglow/Event913/spectra/spec_042_tin-12300.000_tend-15500.000.txt">
      <parameter scale="1e+00" name="Normalization" min="1e-7" max="1000" free="1" value="1.00000" />
    </spectrum>
    <spatialModel type="SkyDirFunction">
      <parameter scale="1.0" name="RA" min="-360" max="360" free="0" value="0" />
      <parameter scale="1.0" name="DEC" min="-90" max="90" free="0" value="0.75" />
    </spatialModel>
    <temporal type="LightCurve" file="/home/irene/cta/models/afterglow/Event913/lightcv/lc_042_tin-12300.000_tend-15500.000.fits">
      <parameter scale="1e+00" name="Normalization" min="0.0" max="1000.0" free="0" value="1.00000" />
    </temporal>
  </source>
  <source type="PointSource" name="Event913_43" tscalc="1">
    <spectrum type="FileFunction" file="/home/irene/cta/models/afterglow/Event913/spectra/spec_043_tin-15500.000_tend-19400.000.txt">
      <parameter scale="1e+00" name="Normalization" min="1e-7" max="1000" free="1" value="1.00000" />
    </spectrum>
    <spatialModel type="SkyDirFunction">
      <parameter scale="1.0" name="RA" min="-360" max="360" free="0" value="0" />
      <parameter scale="1.0" name="DEC" min="-90" max="90" free="0" value="0.75" />
    </spatialModel>
    <temporal type="LightCurve" file="/home/irene/cta/models/afterglow/Event913/lightcv/lc_043_tin-15500.000_tend-19400.000.fits">
      <parameter scale="1e+00" name="Normalization" min="0.0" max="1000.0" free="0" value="1.00000" />
    </temporal>
  </source>
  <source type="PointSource" name="Event913_44" tscalc="1">
    <spectrum type="FileFunction" file="/home/irene/cta/models/afterglow/Event913/spectra/spec_044_tin-19400.000_tend-24300.000.txt">
      <parameter scale="1e+00" name="Normalization" min="1e-7" max="1000" free="1" value="1.00000" />
    </spectrum>
    <spatialModel type="SkyDirFunction">
      <parameter scale="1.0" name="RA" min="-360" max="360" free="0" value="0" />
      <parameter scale="1.0" name="DEC" min="-90" max="90" free="0" value="0.75" />
    </spatialModel>
    <temporal type="LightCurve" file="/home/irene/cta/models/afterglow/Event913/lightcv/lc_044_tin-19400.000_tend-24300.000.fits">
      <parameter scale="1e+00" name="Normalization" min="0.0" max="1000.0" free="0" value="1.00000" />
    </temporal>
  </source>
  <source type="PointSource" name="Event913_45" tscalc="1">
    <spectrum type="FileFunction" file="/home/irene/cta/models/afterglow/Event913/spectra/spec_045_tin-24300.000_tend-30400.000.txt">
      <parameter scale="1e+00" name="Normalization" min="1e-7" max="1000" free="1" value="1.00000" />
    </spectrum>
    <spatialModel type="SkyDirFunction">
      <parameter scale="1.0" name="RA" min="-360" max="360" free="0" value="0" />
      <parameter scale="1.0" name="DEC" min="-90" max="90" free="0" value="0.75" />
    </spatialModel>
    <temporal type="LightCurve" file="/home/irene/cta/models/afterglow/Event913/lightcv/lc_045_tin-24300.000_tend-30400.000.fits">
      <parameter scale="1e+00" name="Normalization" min="0.0" max="1000.0" free="0" value="1.00000" />
    </temporal>
  </source>
  <source type="PointSource" name="Event913_46" tscalc="1">
    <spectrum type="FileFunction" file="/home/irene/cta/models/afterglow/Event913/spectra/spec_046_tin-30400.000_tend-38100.000.txt">
      <parameter scale="1e+00" name="Normalization" min="1e-7" max="1000" free="1" value="1.00000" />
    </spectrum>
    <spatialModel type="SkyDirFunction">
      <parameter scale="1.0" name="RA" min="-360" max="360" free="0" value="0" />
      <parameter scale="1.0" name="DEC" min="-90" max="90" free="0" value="0.75" />
    </spatialModel>
    <temporal type="LightCurve" file="/home/irene/cta/models/afterglow/Event913/lightcv/lc_046_tin-30400.000_tend-38100.000.fits">
      <parameter scale="1e+00" name="Normalization" min="0.0" max="1000.0" free="0" value="1.00000" />
    </temporal>
  </source>
  <source type="PointSource" name="Event913_47" tscalc="1">
    <spectrum type="FileFunction" file="/home/irene/cta/models/afterglow/Event913/spectra/spec_047_tin-38100.000_tend-47700.000.txt">
      <parameter scale="1e+00" name="Normalization" min="1e-7" max="1000" free="1" value="1.00000" />
    </spectrum>
    <spatialModel type="SkyDirFunction">
      <parameter scale="1.0" name="RA" min="-360" max="360" free="0" value="0" />
      <parameter scale="1.0" name="DEC" min="-90" max="90" free="0" value="0.75" />
    </spatialModel>
    <temporal type="LightCurve" file="/home/irene/cta/models/afterglow/Event913/lightcv/lc_047_tin-38100.000_tend-47700.000.fits">
      <parameter scale="1e+00" name="Normalization" min="0.0" max="1000.0" free="0" value="1.00000" />
    </temporal>
  </source>
  <source type="PointSource" name="Event913_48" tscalc="1">
    <spectrum type="FileFunction" file="/home/irene/cta/models/afterglow/Event913/spectra/spec_048_tin-47700.000_tend-59800.000.txt">
      <parameter scale="1e+00" name="Normalization" min="1e-7" max="1000" free="1" value="1.00000" />
    </spectrum>
    <spatialModel type="SkyDirFunction">
      <parameter scale="1.0" name="RA" min="-360" max="360" free="0" value="0" />
      <parameter scale="1.0" name="DEC" min="-90" max="90" free="0" value="0.75" />
    </spatialModel>
    <temporal type="LightCurve" file="/home/irene/cta/models/afterglow/Event913/lightcv/lc_048_tin-47700.000_tend-59800.000.fits">
      <parameter scale="1e+00" name="Normalization" min="0.0" max="1000.0" free="0" value="1.00000" />
    </temporal>
  </source>
  <source type="PointSource" name="Event913_49" tscalc="1">
    <spectrum type="FileFunction" file="/home/irene/cta/models/afterglow/Event913/spectra/spec_049_tin-59800.000_tend-75000.000.txt">
      <parameter scale="1e+00" name="Normalization" min="1e-7" max="1000" free="1" value="1.00000" />
    </spectrum>
    <spatialModel type="SkyDirFunction">
      <parameter scale="1.0" name="RA" min="-360" max="360" free="0" value="0" />
      <parameter scale="1.0" name="DEC" min="-90" max="90" free="0" value="0.75" />
    </spatialModel>
    <temporal type="LightCurve" file="/home/irene/cta/models/afterglow/Event913/lightcv/lc_049_tin-59800.000_tend-75000.000.fits">
      <parameter scale="1e+00" name="Normalization" min="0.0" max="1000.0" free="0" value="1.00000" />
    </temporal>
  </source>
  <source type="PointSource" name="Event913_50" tscalc="1">
    <spectrum type="FileFunction" file="/home/irene/cta/models/afterglow/Event913/spectra/spec_050_tin-75000.000_tend-93800.000.txt">
      <parameter scale="1e+00" name="Normalization" min="1e-7" max="1000" free="1" value="1.00000" />
    </spectrum>
    <spatialModel type="SkyDirFunction">
      <parameter scale="1.0" name="RA" min="-360" max="360" free="0" value="0" />
      <parameter scale="1.0" name="DEC" min="-90" max="90" free="0" value="0.75" />
    </spatialModel>
    <temporal type="LightCurve" file="/home/irene/cta/models/afterglow/Event913/lightcv/lc_050_tin-75000.000_tend-93800.000.fits">
      <parameter scale="1e+00" name="Normalization" min="0.0" max="1000.0" free="0" value="1.00000" />
    </temporal>
  </source>
  <source type="PointSource" name="Event913_51" tscalc="1">
    <spectrum type="FileFunction" file="/home/irene/cta/models/afterglow/Event913/spectra/spec_051_tin-93800.000_tend-117000.000.txt">
      <parameter scale="1e+00" name="Normalization" min="1e-7" max="1000" free="1" value="1.00000" />
    </spectrum>
    <spatialModel type="SkyDirFunction">
      <parameter scale="1.0" name="RA" min="-360" max="360" free="0" value="0" />
      <parameter scale="1.0" name="DEC" min="-90" max="90" free="0" value="0.75" />
    </spatialModel>
    <temporal type="LightCurve" file="/home/irene/cta/models/afterglow/Event913/lightcv/lc_051_tin-93800.000_tend-117000.000.fits">
      <parameter scale="1e+00" name="Normalization" min="0.0" max="1000.0" free="0" value="1.00000" />
    </temporal>
  </source>
  <source type="PointSource" name="Event913_52" tscalc="1">
    <spectrum type="FileFunction" file="/home/irene/cta/models/afterglow/Event913/spectra/spec_052_tin-117000.000_tend-147000.000.txt">
      <parameter scale="1e+00" name="Normalization" min="1e-7" max="1000" free="1" value="1.00000" />
    </spectrum>
    <spatialModel type="SkyDirFunction">
      <parameter scale="1.0" name="RA" min="-360" max="360" free="0" value="0" />
      <parameter scale="1.0" name="DEC" min="-90" max="90" free="0" value="0.75" />
    </spatialModel>
    <temporal type="LightCurve" file="/home/irene/cta/models/afterglow/Event913/lightcv/lc_052_tin-117000.000_tend-147000.000.fits">
      <parameter scale="1e+00" name="Normalization" min="0.0" max="1000.0" free="0" value="1.00000" />
    </temporal>
  </source>
</source_library>
